[{"Pos":"1","Driver":"Ayrton Senna","Nationality":"BRA","Car":"McLaren Honda","PTS":"90"},{"Pos":"2","Driver":"Alain Prost","Nationality":"FRA","Car":"McLaren Honda","PTS":"87"},{"Pos":"3","Driver":"Gerhard Berger","Nationality":"AUT","Car":"Ferrari","PTS":"41"},{"Pos":"4","Driver":"Thierry Boutsen","Nationality":"BEL","Car":"Benetton Ford","PTS":"27"},{"Pos":"5","Driver":"Michele Alboreto","Nationality":"ITA","Car":"Ferrari","PTS":"24"},{"Pos":"6","Driver":"Nelson Piquet","Nationality":"BRA","Car":"Lotus Honda","PTS":"22"},{"Pos":"7","Driver":"Ivan Capelli","Nationality":"ITA","Car":"March Judd","PTS":"17"},{"Pos":"8","Driver":"Derek Warwick","Nationality":"GBR","Car":"Arrows Megatron","PTS":"17"},{"Pos":"9","Driver":"Nigel Mansell","Nationality":"GBR","Car":"Williams Judd","PTS":"12"},{"Pos":"10","Driver":"Alessandro Nannini","Nationality":"ITA","Car":"Benetton Ford","PTS":"12"},{"Pos":"11","Driver":"Riccardo Patrese","Nationality":"ITA","Car":"Williams Judd","PTS":"8"},{"Pos":"12","Driver":"Eddie  Cheever","Nationality":"USA","Car":"Arrows Megatron","PTS":"6"},{"Pos":"13","Driver":"Mauricio Gugelmin","Nationality":"BRA","Car":"March Judd","PTS":"5"},{"Pos":"14","Driver":"Jonathan  Palmer","Nationality":"GBR","Car":"Tyrrell Ford","PTS":"5"},{"Pos":"15","Driver":"Andrea de Cesaris","Nationality":"ITA","Car":"Rial Ford","PTS":"3"},{"Pos":"16","Driver":"Pierluigi Martini","Nationality":"ITA","Car":"Minardi Ford","PTS":"1"},{"Pos":"17","Driver":"Satoru Nakajima","Nationality":"JPN","Car":"Lotus Honda","PTS":"1"}]