[{"GrandPrix":"Australia","Driver":"Nico Rosberg","Car":"Williams Toyota","Time":"1:27.706"},{"GrandPrix":"Malaysia","Driver":"Jenson Button","Car":"Brawn Mercedes","Time":"1:36.641"},{"GrandPrix":"China","Driver":"Rubens Barrichello","Car":"Brawn Mercedes","Time":"1:52.592"},{"GrandPrix":"Bahrain","Driver":"Jarno Trulli","Car":"Toyota","Time":"1:34.556"},{"GrandPrix":"Spain","Driver":"Rubens Barrichello","Car":"Brawn Mercedes","Time":"1:22.762"},{"GrandPrix":"Monaco","Driver":"Felipe Massa","Car":"Ferrari","Time":"1:15.154"},{"GrandPrix":"Turkey","Driver":"Jenson Button","Car":"Brawn Mercedes","Time":"1:27.579"},{"GrandPrix":"Great Britain","Driver":"Sebastian Vettel","Car":"RBR Renault","Time":"1:20.735"},{"GrandPrix":"Germany","Driver":"Fernando Alonso","Car":"Renault","Time":"1:33.365"},{"GrandPrix":"Hungary","Driver":"Mark Webber","Car":"RBR Renault","Time":"1:21.931"},{"GrandPrix":"Europe","Driver":"Timo Glock","Car":"Toyota","Time":"1:38.683"},{"GrandPrix":"Belgium","Driver":"Sebastian Vettel","Car":"RBR Renault","Time":"1:47.263"},{"GrandPrix":"Italy","Driver":"Adrian Sutil","Car":"Force India Mercedes","Time":"1:24.739"},{"GrandPrix":"Singapore","Driver":"Fernando Alonso","Car":"Renault","Time":"1:48.240"},{"GrandPrix":"Japan","Driver":"Mark Webber","Car":"RBR Renault","Time":"1:32.569"},{"GrandPrix":"Brazil","Driver":"Mark Webber","Car":"RBR Renault","Time":"1:13.733"},{"GrandPrix":"Abu Dhabi","Driver":"Sebastian Vettel","Car":"RBR Renault","Time":"1:40.279"}]