[{"GrandPrix":"Austria","Driver":"Lando Norris","Car":"McLaren Renault","Time":"1:07.475"},{"GrandPrix":"Styria","Driver":"Carlos Sainz","Car":"McLaren Renault","Time":"1:05.619"},{"GrandPrix":"Hungary","Driver":"Lewis Hamilton","Car":"Mercedes","Time":"1:16.627"},{"GrandPrix":"Great Britain","Driver":"Max Verstappen","Car":"Red Bull Racing Honda","Time":"1:27.097"},{"GrandPrix":"70th Anniversary","Driver":"Lewis Hamilton","Car":"Mercedes","Time":"1:28.451"},{"GrandPrix":"Spain","Driver":"Valtteri Bottas","Car":"Mercedes","Time":"1:18.183"},{"GrandPrix":"Belgium","Driver":"Daniel Ricciardo","Car":"Renault","Time":"1:47.483"},{"GrandPrix":"Italy","Driver":"Lewis Hamilton","Car":"Mercedes","Time":"1:22.746"},{"GrandPrix":"Tuscany","Driver":"Lewis Hamilton","Car":"Mercedes","Time":"1:18.833"},{"GrandPrix":"Russia","Driver":"Valtteri Bottas","Car":"Mercedes","Time":"1:37.030"},{"GrandPrix":"Eifel","Driver":"Max Verstappen","Car":"Red Bull Racing Honda","Time":"1:28.139"},{"GrandPrix":"Portugal","Driver":"Lewis Hamilton","Car":"Mercedes","Time":"1:18.750"},{"GrandPrix":"Emilia Romagna","Driver":"Lewis Hamilton","Car":"Mercedes","Time":"1:15.484"},{"GrandPrix":"Turkey","Driver":"Lando Norris","Car":"McLaren Renault","Time":"1:36.806"},{"GrandPrix":"Bahrain","Driver":"Max Verstappen","Car":"Red Bull Racing Honda","Time":"1:32.014"},{"GrandPrix":"Sakhir","Driver":"George Russell","Car":"Mercedes","Time":"55.404"},{"GrandPrix":"Abu Dhabi","Driver":"Daniel Ricciardo","Car":"Renault","Time":"1:40.926"}]