[{"GrandPrix":"Australia","Date":"27 Mar 2011","Winner":"Sebastian Vettel","Car":"Red Bull Racing Renault","Laps":"58","Time":"1:29:30.259"},{"GrandPrix":"Malaysia","Date":"10 Apr 2011","Winner":"Sebastian Vettel","Car":"Red Bull Racing Renault","Laps":"56","Time":"1:37:39.832"},{"GrandPrix":"China","Date":"17 Apr 2011","Winner":"Lewis Hamilton","Car":"McLaren Mercedes","Laps":"56","Time":"1:36:58.226"},{"GrandPrix":"Turkey","Date":"08 May 2011","Winner":"Sebastian Vettel","Car":"Red Bull Racing Renault","Laps":"58","Time":"1:30:17.558"},{"GrandPrix":"Spain","Date":"22 May 2011","Winner":"Sebastian Vettel","Car":"Red Bull Racing Renault","Laps":"66","Time":"1:39:03.301"},{"GrandPrix":"Monaco","Date":"29 May 2011","Winner":"Sebastian Vettel","Car":"Red Bull Racing Renault","Laps":"78","Time":"2:09:38.373"},{"GrandPrix":"Canada","Date":"12 Jun 2011","Winner":"Jenson Button","Car":"McLaren Mercedes","Laps":"70","Time":"4:04:39.537"},{"GrandPrix":"Europe","Date":"26 Jun 2011","Winner":"Sebastian Vettel","Car":"Red Bull Racing Renault","Laps":"57","Time":"1:39:36.169"},{"GrandPrix":"Great Britain","Date":"10 Jul 2011","Winner":"Fernando Alonso","Car":"Ferrari","Laps":"52","Time":"1:28:41.196"},{"GrandPrix":"Germany","Date":"24 Jul 2011","Winner":"Lewis Hamilton","Car":"McLaren Mercedes","Laps":"60","Time":"1:37:30.334"},{"GrandPrix":"Hungary","Date":"31 Jul 2011","Winner":"Jenson Button","Car":"McLaren Mercedes","Laps":"70","Time":"1:46:42.337"},{"GrandPrix":"Belgium","Date":"28 Aug 2011","Winner":"Sebastian Vettel","Car":"Red Bull Racing Renault","Laps":"44","Time":"1:26:44.893"},{"GrandPrix":"Italy","Date":"11 Sep 2011","Winner":"Sebastian Vettel","Car":"Red Bull Racing Renault","Laps":"53","Time":"1:20:46.172"},{"GrandPrix":"Singapore","Date":"25 Sep 2011","Winner":"Sebastian Vettel","Car":"Red Bull Racing Renault","Laps":"61","Time":"1:59:06.757"},{"GrandPrix":"Japan","Date":"09 Oct 2011","Winner":"Jenson Button","Car":"McLaren Mercedes","Laps":"53","Time":"1:30:53.427"},{"GrandPrix":"South Korea","Date":"16 Oct 2011","Winner":"Sebastian Vettel","Car":"Red Bull Racing Renault","Laps":"55","Time":"1:38:01.994"},{"GrandPrix":"India","Date":"30 Oct 2011","Winner":"Sebastian Vettel","Car":"Red Bull Racing Renault","Laps":"60","Time":"1:30:35.002"},{"GrandPrix":"Abu Dhabi","Date":"13 Nov 2011","Winner":"Lewis Hamilton","Car":"McLaren Mercedes","Laps":"55","Time":"1:37:11.886"},{"GrandPrix":"Brazil","Date":"27 Nov 2011","Winner":"Mark Webber","Car":"Red Bull Racing Renault","Laps":"71","Time":"1:32:17.464"}]