[{"GrandPrix":"Argentina","Date":"17 Jan 1954","Winner":"Juan Manuel Fangio","Car":"Maserati","Laps":"87","Time":"3:00:55.800"},{"GrandPrix":"Indianapolis 500","Date":"31 May 1954","Winner":"Bill  Vukovich","Car":"Kurtis Kraft Offenhauser","Laps":"200","Time":"3:49:17.270"},{"GrandPrix":"Belgium","Date":"20 Jun 1954","Winner":"Juan Manuel Fangio","Car":"Maserati","Laps":"36","Time":"2:44:42.400"},{"GrandPrix":"France","Date":"04 Jul 1954","Winner":"Juan Manuel Fangio","Car":"Mercedes-Benz","Laps":"61","Time":"2:42:47.900"},{"GrandPrix":"Great Britain","Date":"17 Jul 1954","Winner":"Jose Froilan Gonzalez","Car":"Ferrari","Laps":"90","Time":"2:56:14.000"},{"GrandPrix":"Germany","Date":"01 Aug 1954","Winner":"Juan Manuel Fangio","Car":"Mercedes-Benz","Laps":"22","Time":"3:45:45.800"},{"GrandPrix":"Switzerland","Date":"22 Aug 1954","Winner":"Juan Manuel Fangio","Car":"Mercedes-Benz","Laps":"66","Time":"3:00:34.500"},{"GrandPrix":"Italy","Date":"05 Sep 1954","Winner":"Juan Manuel Fangio","Car":"Mercedes-Benz","Laps":"80","Time":"2:47:47.900"},{"GrandPrix":"Spain","Date":"24 Oct 1954","Winner":"Mike Hawthorn","Car":"Ferrari","Laps":"80","Time":"3:13:52.100"}]